<?xml version="1.0" encoding="UTF-8"?>
<sbml xmlns="http://www.sbml.org/sbml/level3/version1/core" xmlns:groups="http://www.sbml.org/sbml/level3/version1/groups/version1" level="3" version="1">
  <model substanceUnits="substance" timeUnits="second" volumeUnits="volume" areaUnits="area" lengthUnits="metre" extentUnits="substance">
    <listOfUnitDefinitions>
      <unitDefinition id="mmol_per_gDW_per_hr">
        <listOfUnits>
          <unit kind="mole" exponent="1" scale="-3" multiplier="1"/>
          <unit kind="gram" exponent="-1" scale="0" multiplier="1"/>
          <unit kind="second" exponent="-1" scale="0" multiplier="0.000277777777777778"/>
        </listOfUnits>
      </unitDefinition>
      <unitDefinition id="volume">
        <listOfUnits>
          <unit kind="litre" exponent="1" scale="0" multiplier="1"/>
        </listOfUnits>
      </unitDefinition>
      <unitDefinition id="substance">
        <listOfUnits>
          <unit kind="mole" exponent="1" scale="0" multiplier="1"/>
        </listOfUnits>
      </unitDefinition>
      <unitDefinition id="area">
        <listOfUnits>
          <unit kind="metre" exponent="2" scale="0" multiplier="1"/>
        </listOfUnits>
      </unitDefinition>
    </listOfUnitDefinitions>
    <listOfCompartments>
      <compartment id="c" name="Cytoplasm" spatialDimensions="3" units="volume" constant="false"/>
      <compartment id="e" name="Extracellular" spatialDimensions="3" units="volume" constant="false"/>
    </listOfCompartments>
    <listOfSpecies>
      <species id="M_cpd00001_c" name="H2O" compartment="c" substanceUnits="substance" hasOnlySubstanceUnits="false" boundaryCondition="false" constant="false">
        <notes>
          <body xmlns="http://www.w3.org/1999/xhtml">
            <p>FORMULA: H2O</p>
            <p>CHARGE: 0</p>
          </body>
        </notes>
      </species>
      <species id="M_cpd00027_c" name="D-Glucose" compartment="c" substanceUnits="substance" hasOnlySubstanceUnits="false" boundaryCondition="false" constant="false">
        <notes>
          <body xmlns="http://www.w3.org/1999/xhtml">
            <p>FORMULA: C6H12O6</p>
            <p>CHARGE: 0</p>
          </body>
        </notes>
      </species>
      <species id="M_cpd00158_c" name="CELB" compartment="c" substanceUnits="substance" hasOnlySubstanceUnits="false" boundaryCondition="false" constant="false">
        <notes>
          <body xmlns="http://www.w3.org/1999/xhtml">
            <p>FORMULA: C12H22O11</p>
            <p>CHARGE: 0</p>
          </body>
        </notes>
      </species>
    </listOfSpecies>
    <listOfReactions>
      <reaction id="R_rxn00222" name="beta-D-Glucoside glucohydrolase" reversible="false" fast="false">
        <notes>
          <body xmlns="http://www.w3.org/1999/xhtml">
            <p>GENE_ASSOCIATION: PA1726</p>
            <p>SUBSYSTEM: Carbohydrate Metabolism</p>
            <p>EC Number: </p>
            <p>Confidence Level: </p>
            <p>AUTHORS: </p>
            <p/>
          </body>
        </notes>
        <listOfReactants>
          <speciesReference species="M_cpd00001_c" stoichiometry="1" constant="true"/>
          <speciesReference species="M_cpd00158_c" stoichiometry="1" constant="true"/>
        </listOfReactants>
        <listOfProducts>
          <speciesReference species="M_cpd00027_c" stoichiometry="2" constant="true"/>
        </listOfProducts>
        <kineticLaw>
          <math xmlns="http://www.w3.org/1998/Math/MathML">
            <ci> FLUX_VALUE </ci>
          </math>
          <listOfLocalParameters>
            <localParameter id="LOWER_BOUND" value="0" units="mmol_per_gDW_per_hr"/>
            <localParameter id="UPPER_BOUND" value="1000" units="mmol_per_gDW_per_hr"/>
            <localParameter id="FLUX_VALUE" value="0" units="mmol_per_gDW_per_hr"/>
            <localParameter id="OBJECTIVE_COEFFICIENT" value="0" units="mmol_per_gDW_per_hr"/>
          </listOfLocalParameters>
        </kineticLaw>
      </reaction>
    </listOfReactions>
    <groups:listOfGroups>
      <groups:group groups:id="s_2d94d9915b416004b88a3f1bf8f3024c" groups:name="Carbohydrate Metabolism" groups:kind="partonomy">
        <groups:listOfMembers>
          <groups:member groups:idRef="R_rxn00222"/>
        </groups:listOfMembers>
      </groups:group>
    </groups:listOfGroups>
  </model>
</sbml>
