{
"metabolites":[
{
"id":"cpd00015_c",
"name":"FAD",
"compartment":"c",
"charge":-2,
"formula":"C27H31N9O15P2"
},
{
"id":"cpd00982_c",
"name":"FADH2",
"compartment":"c",
"charge":-2,
"formula":"C27H33N9O15P2"
},
{
"id":"cpd00003_c",
"name":"NAD",
"compartment":"c",
"charge":-1,
"formula":"C21H26N7O14P2"
},
{
"id":"cpd00004_c",
"name":"NADH",
"compartment":"c",
"charge":-2,
"formula":"C21H27N7O14P2"
},
{
"id":"cpd00067_c",
"name":"H+",
"compartment":"c",
"charge":1,
"formula":"H"
},
{
"id":"cpd00001_c",
"name":"H2O",
"compartment":"c",
"formula":"H2O"
},
{
"id":"cpd00006_c",
"name":"NADP",
"compartment":"c",
"charge":-2,
"formula":"C21H26N7O17P3"
},
{
"id":"cpd00005_c",
"name":"NADPH",
"compartment":"c",
"charge":-3,
"formula":"C21H27N7O17P3"
},
{
"id":"cpd00080_c",
"name":"Glycerol-3-phosphate",
"compartment":"c",
"charge":-1,
"formula":"C3H8O6P"
},
{
"id":"cpd00095_c",
"name":"Glycerone-phosphate",
"compartment":"c",
"charge":-1,
"formula":"C3H6O6P"
},
{
"id":"cpd00011_c",
"name":"CO2",
"compartment":"c",
"formula":"CO2"
},
{
"id":"cpd00009_c",
"name":"Phosphate",
"compartment":"c",
"charge":-2,
"formula":"HO4P"
},
{
"id":"cpd00071_c",
"name":"Acetaldehyde",
"compartment":"c",
"formula":"C2H4O"
},
{
"id":"cpd00098_c",
"name":"Choline",
"compartment":"c",
"charge":1,
"formula":"C5H14NO"
},
{
"id":"cpd00013_c",
"name":"NH3",
"compartment":"c",
"charge":1,
"formula":"H4N"
},
{
"id":"cpd00100_c",
"name":"Glycerol",
"compartment":"c",
"formula":"C3H8O3"
},
{
"id":"cpd00012_c",
"name":"PPi",
"compartment":"c",
"charge":-2,
"formula":"H2O7P2"
},
{
"id":"cpd02090_c",
"name":"Glycerophosphoglycerol",
"compartment":"c",
"charge":-1,
"formula":"C6H14O8P"
},
{
"id":"cpd00052_c",
"name":"CTP",
"compartment":"c",
"charge":-3,
"formula":"C9H13N3O14P3"
},
{
"id":"cpd15417_c",
"name":"CDP-1,2-didodecanoylglycerol",
"compartment":"c",
"charge":-2,
"formula":"C36H63N3O15P2"
},
{
"id":"cpd15423_c",
"name":"CDP-1,2-ditetradecanoylglycerol",
"compartment":"c",
"charge":-2,
"formula":"C40H71N3O15P2"
},
{
"id":"cpd15422_c",
"name":"CDP-1,2-ditetradec-7-enoylglycerol",
"compartment":"c",
"charge":-2,
"formula":"C40H67N3O15P2"
},
{
"id":"cpd15418_c",
"name":"CDP-1,2-dihexadec-9-enoylglycerol",
"compartment":"c",
"charge":-2,
"formula":"C44H75N3O15P2"
},
{
"id":"cpd15421_c",
"name":"CDP-1,2-dioctadecanoylglycerol",
"compartment":"c",
"charge":-2,
"formula":"C48H87N3O15P2"
},
{
"id":"cpd15420_c",
"name":"CDP-1,2-dioctadec-11-enoylglycerol",
"compartment":"c",
"charge":-2,
"formula":"C48H83N3O15P2"
},
{
"id":"cpd15536_c",
"name":"Phosphatidylglycerol_ditetradecanoyl",
"compartment":"c",
"charge":-1,
"formula":"C34H66O10P"
},
{
"id":"cpd15538_c",
"name":"Phosphatidylglycerol_dihexadecanoyl",
"compartment":"c",
"charge":-1,
"formula":"C38H74O10P"
},
{
"id":"cpd15540_c",
"name":"Phosphatidylglycerol_dioctadecanoyl",
"compartment":"c",
"charge":-1,
"formula":"C42H82O10P"
},
{
"id":"cpd11422_c",
"name":"1,2-diacyl-sn-glycerol 3-phosphate",
"compartment":"c",
"charge":-1,
"formula":"C5H6O8PR2"
},
{
"id":"cpd00054_c",
"name":"L-Serine",
"compartment":"c",
"formula":"C3H7NO3"
},
{
"id":"cPY00131_c",
"name":"pg160161",
"compartment":"c",
"formula":"C38H72O10P1"
},
{
"id":"cPY00142_c",
"name":"clpn160161",
"compartment":"c",
"formula":"C73H136O17P2"
},
{
"id":"cpd15428_c",
"name":"clpn160",
"compartment":"c",
"charge":-2,
"formula":"C73H140O17P2"
},
{
"id":"cpd15539_c",
"name":"Phosphatidylglycerol_dihexadec-9-enoyl",
"compartment":"c",
"charge":-1,
"formula":"C38H70O10P"
},
{
"id":"cpd15429_c",
"name":"clpn161",
"compartment":"c",
"charge":-2,
"formula":"C73H132O17P2"
},
{
"id":"cPY00134_c",
"name":"pg180181",
"compartment":"c",
"formula":"C42H80O10P1"
},
{
"id":"cPY00141_c",
"name":"clpn180181",
"compartment":"c",
"formula":"C81H150O17P2"
},
{
"id":"cpd15430_c",
"name":"clpn180",
"compartment":"c",
"charge":-2,
"formula":"C81H156O17P2"
},
{
"id":"cpd15541_c",
"name":"Phosphatidylglycerol_dioctadec-11-enoyl",
"compartment":"c",
"charge":-1,
"formula":"C42H78O10P"
},
{
"id":"cpd15431_c",
"name":"clpn181",
"compartment":"c",
"charge":-2,
"formula":"C81H148O17P2"
},
{
"id":"cpd00046_c",
"name":"CMP",
"compartment":"c",
"charge":-1,
"formula":"C9H13N3O8P"
},
{
"id":"cpd15419_c",
"name":"CDP-1,2-dihexadecanoylglycerol",
"compartment":"c",
"charge":-2,
"formula":"C44H79N3O15P2"
},
{
"id":"cpd00162_c",
"name":"Aminoethanol",
"compartment":"c",
"charge":1,
"formula":"C2H8NO"
},
{
"id":"cpd00908_c",
"name":"Glycerophosphoethanolamine",
"compartment":"c",
"formula":"C5H14NO6P"
},
{
"id":"cpd00507_c",
"name":"Glycerophosphocholine",
"compartment":"c",
"formula":"C8H20NO6P"
},
{
"id":"cpd11427_c",
"name":"CDP-diacylglycerol",
"compartment":"c",
"charge":-2,
"formula":"C14H17N3O15P2R2"
},
{
"id":"cpd11652_c",
"name":"Phosphatidylglycerol",
"compartment":"c",
"charge":-1,
"formula":"C8H12O10PR2"
},
{
"id":"cpd12801_c",
"name":"Cardiolipin",
"compartment":"c",
"charge":-2,
"formula":"C13H16O17P2R4"
},
{
"id":"cpd11454_c",
"name":"Phosphatidylglycerophosphate",
"compartment":"c",
"charge":-2,
"formula":"C8H12O13P2R2"
},
{
"id":"cpd15542_c",
"name":"Phosphatidylglycerophosphate_didodecanoyl",
"compartment":"c",
"charge":-2,
"formula":"C30H58O13P2"
},
{
"id":"cpd15543_c",
"name":"Phosphatidylglycerophosphate_ditetradecanoyl",
"compartment":"c",
"charge":-2,
"formula":"C34H66O13P2"
},
{
"id":"cpd15544_c",
"name":"Phosphatidylglycerophosphate_ditetradec-7-enoyl",
"compartment":"c",
"charge":-2,
"formula":"C34H62O13P2"
},
{
"id":"cpd15545_c",
"name":"Phosphatidylglycerophosphate_dihexadecanoyl",
"compartment":"c",
"charge":-2,
"formula":"C38H74O13P2"
},
{
"id":"cpd15546_c",
"name":"Phosphatidylglycerophosphate_dihexadec-9-enoyl",
"compartment":"c",
"charge":-2,
"formula":"C38H70O13P2"
},
{
"id":"cpd15547_c",
"name":"Phosphatidylglycerophosphate_dioctadecanoyl",
"compartment":"c",
"charge":-2,
"formula":"C42H82O13P2"
},
{
"id":"cpd15548_c",
"name":"Phosphatidylglycerophosphate_dioctadec-11-enoyl",
"compartment":"c",
"charge":-2,
"formula":"C42H78O13P2"
},
{
"id":"cpd11624_c",
"name":"Lecithin",
"compartment":"c",
"formula":"C10H18NO8PR2"
},
{
"id":"cpd15535_c",
"name":"Phosphatidylglycerol_didodecanoyl",
"compartment":"c",
"charge":-1,
"formula":"C30H58O10P"
},
{
"id":"cpd15537_c",
"name":"Phosphatidylglycerol_ditetradec-7-enoyl",
"compartment":"c",
"charge":-1,
"formula":"C34H62O10P"
},
{
"id":"cpd15690_c",
"name":"Dianteisoheptadecanoylphosphatidylserine",
"compartment":"c",
"charge":-2,
"formula":"C40H76NO10P"
},
{
"id":"cpd15693_c",
"name":"Dianteisopentadecanoylphosphatidylserine",
"compartment":"c",
"charge":-2,
"formula":"C36H68NO10P"
},
{
"id":"cpd11455_c",
"name":"ps_BS",
"compartment":"c",
"charge":-2,
"formula":"C8H10NO10PR2"
},
{
"id":"cpd15689_c",
"name":"Diisoheptadecanoylphosphatidylserine",
"compartment":"c",
"charge":-2,
"formula":"C40H76NO10P"
},
{
"id":"cpd15694_c",
"name":"Diisohexadecanoylphosphatidylserine",
"compartment":"c",
"charge":-2,
"formula":"C38H72NO10P"
},
{
"id":"cpd15692_c",
"name":"Diisopentadecanoylphosphatidylserine",
"compartment":"c",
"charge":-2,
"formula":"C36H68NO10P"
},
{
"id":"cpd15691_c",
"name":"Diisotetradecanoylphosphatidylserine",
"compartment":"c",
"charge":-2,
"formula":"C34H64NO10P"
},
{
"id":"cpd15552_c",
"name":"phosphatidylserine_didodecanoyl",
"compartment":"c",
"charge":-2,
"formula":"C30H56NO10P"
},
{
"id":"cpd15553_c",
"name":"phosphatidylserine_ditetradecanoyl",
"compartment":"c",
"charge":-2,
"formula":"C34H64NO10P"
},
{
"id":"cpd15554_c",
"name":"phosphatidylserine_ditetradec-7-enoyl",
"compartment":"c",
"charge":-2,
"formula":"C34H60NO10P"
},
{
"id":"cPY00122_c",
"name":"ps160161",
"compartment":"c",
"formula":"C38H71N1O10P1"
},
{
"id":"cpd15555_c",
"name":"phosphatidylserine_dihexadecanoyl",
"compartment":"c",
"charge":-2,
"formula":"C38H72NO10P"
},
{
"id":"cpd15556_c",
"name":"phosphatidylserine_dihexadec-9-enoyl",
"compartment":"c",
"charge":-2,
"formula":"C38H68NO10P"
},
{
"id":"cPY00127_c",
"name":"ps180181",
"compartment":"c",
"formula":"C42H79N1O10P1"
},
{
"id":"cpd15557_c",
"name":"phosphatidylserine_dioctadecanoyl",
"compartment":"c",
"charge":-2,
"formula":"C42H80NO10P"
},
{
"id":"cpd15558_c",
"name":"phosphatidylserine_dioctadec-11-enoyl",
"compartment":"c",
"charge":-2,
"formula":"C42H76NO10P"
},
{
"id":"cpd15696_c",
"name":"Dianteisoheptadecanoylphosphatidylethanolamine",
"compartment":"c",
"formula":"C39H78NO8P"
},
{
"id":"cpd15699_c",
"name":"Dianteisopentadecanoylphosphatidylethanolamine",
"compartment":"c",
"formula":"C35H70NO8P"
},
{
"id":"cpd15695_c",
"name":"Diisoheptadecanoylphosphatidylethanolamine",
"compartment":"c",
"formula":"C39H78NO8P"
},
{
"id":"cpd15700_c",
"name":"Diisohexadecanoylphosphatidylethanolamine",
"compartment":"c",
"formula":"C37H74NO8P"
},
{
"id":"cpd15698_c",
"name":"Diisopentadecanoylphosphatidylethanolamine",
"compartment":"c",
"formula":"C35H70NO8P"
},
{
"id":"cpd15697_c",
"name":"Diisotetradecanoylphosphatidylethanolamine",
"compartment":"c",
"formula":"C33H66NO8P"
},
{
"id":"cpd11456_c",
"name":"Phosphatidylethanolamine",
"compartment":"c",
"charge":-1,
"formula":"C7H11NO8PR2"
},
{
"id":"cpd15528_c",
"name":"phosphatidylethanolamine_didodecanoyl",
"compartment":"c",
"formula":"C29H58NO8P"
},
{
"id":"cpd15529_c",
"name":"phosphatidylethanolamine_ditetradecanoyl",
"compartment":"c",
"formula":"C33H66NO8P"
},
{
"id":"cpd15530_c",
"name":"phosphatidylethanolamine_ditetradec-7-enoyl",
"compartment":"c",
"formula":"C33H62NO8P"
},
{
"id":"cPY00123_c",
"name":"pe160161",
"compartment":"c",
"formula":"C37H72N1O8P1"
},
{
"id":"cpd15531_c",
"name":"phosphatidylethanolamine_dihexadecanoyl",
"compartment":"c",
"formula":"C37H74NO8P"
},
{
"id":"cpd15532_c",
"name":"phosphatidylethanolamine_dihexadec-9enoyl",
"compartment":"c",
"formula":"C37H70NO8P"
},
{
"id":"cPY00128_c",
"name":"pe180181",
"compartment":"c",
"formula":"C41H80N1O8P1"
},
{
"id":"cpd15533_c",
"name":"phosphatidylethanolamine_dioctadecanoyl",
"compartment":"c",
"formula":"C41H82NO8P"
},
{
"id":"cpd15534_c",
"name":"phosphatidylethanolamine_dioctadec-11-enoyl",
"compartment":"c",
"formula":"C41H78NO8P"
}
],
"reactions":[
{
"id":"rxn00616",
"name":"sn-Glycerol-3-phosphate(acceptor) 2-oxidoreductase",
"metabolites":{
"cpd00015_c":-1.0,
"cpd00080_c":-1.0,
"cpd00095_c":1.0,
"cpd00982_c":1.0
},
"lower_bound":-1000.0,
"upper_bound":1000.0,
"gene_reaction_rule":"((PA3584) or (PA3025))",
"subsystem":"Glycerophospholipid metabolism",
"notes":{
"AUTHORS":[
""
],
"CONFIDENCE LEVEL":[
""
],
"EC NUMBER":[
"1.1.99.5"
],
"GENE ASSOCIATION":[
"((PA3584) or (PA3025))"
]
}
},
{
"id":"rxn00611",
"name":"glycerol-3-phosphate dehydrogenase (NAD)",
"metabolites":{
"cpd00003_c":1.0,
"cpd00004_c":-1.0,
"cpd00067_c":-1.0,
"cpd00080_c":1.0,
"cpd00095_c":-1.0
},
"lower_bound":-1000.0,
"upper_bound":1000.0,
"gene_reaction_rule":"PA1614",
"subsystem":"Glycerophospholipid metabolism",
"notes":{
"AUTHORS":[
""
],
"CONFIDENCE LEVEL":[
""
],
"EC NUMBER":[
"1.1.1.261,1.1.1.94"
],
"GENE ASSOCIATION":[
"PA1614"
]
}
},
{
"id":"rxn00612",
"name":"glycerol-3-phosphate dehydrogenase (NADP)",
"metabolites":{
"cpd00005_c":-1.0,
"cpd00006_c":1.0,
"cpd00067_c":-1.0,
"cpd00080_c":1.0,
"cpd00095_c":-1.0
},
"lower_bound":-1000.0,
"upper_bound":1000.0,
"gene_reaction_rule":"PA1614",
"subsystem":"Glycerophospholipid metabolism",
"notes":{
"AUTHORS":[
""
],
"CONFIDENCE LEVEL":[
""
],
"EC NUMBER":[
"1.1.1.261,1.1.1.94"
],
"GENE ASSOCIATION":[
"PA1614"
]
}
},
{
"id":"rxn08669",
"name":"Glycerophosphodiester phosphodiesterase (Glycerophosphoglycerol)",
"metabolites":{
"cpd00001_c":-1.0,
"cpd00080_c":1.0,
"cpd00100_c":1.0,
"cpd02090_c":-1.0
},
"lower_bound":-1000.0,
"upper_bound":1000.0,
"gene_reaction_rule":"((PA2352) or (PA0347))",
"subsystem":"Glycerophospholipid metabolism",
"notes":{
"AUTHORS":[
""
],
"CONFIDENCE LEVEL":[
""
],
"EC NUMBER":[
"3.1.4.46"
],
"GENE ASSOCIATION":[
"((PA2352) or (PA0347))"
]
}
},
{
"id":"rPY00184",
"name":"Cardiolipin synthase (n-C16:0 16:1)",
"metabolites":{
"cPY00131_c":-2.0,
"cPY00142_c":1.0,
"cpd00100_c":1.0
},
"lower_bound":-1000.0,
"upper_bound":1000.0,
"gene_reaction_rule":"(PA2155) or (PA5394)",
"subsystem":"Glycerophospholipid metabolism",
"notes":{
"AUTHORS":[
""
],
"CONFIDENCE LEVEL":[
""
],
"EC NUMBER":[
"2.7.8.-"
],
"GENE ASSOCIATION":[
"(PA2155) or (PA5394)"
]
}
},
{
"id":"rxn08229",
"name":"Cardiolipin synthase (n-C16:0)",
"metabolites":{
"cpd00100_c":1.0,
"cpd15428_c":1.0,
"cpd15538_c":-2.0
},
"lower_bound":-1000.0,
"upper_bound":1000.0,
"gene_reaction_rule":"(PA2155) or (PA5394)",
"subsystem":"Glycerophospholipid metabolism",
"notes":{
"AUTHORS":[
""
],
"CONFIDENCE LEVEL":[
""
],
"EC NUMBER":[
"2.7.8.-"
],
"GENE ASSOCIATION":[
"(PA2155) or (PA5394)"
]
}
},
{
"id":"rxn08230",
"name":"Cardiolipin synthase (n-C16:1)",
"metabolites":{
"cpd00100_c":1.0,
"cpd15429_c":1.0,
"cpd15539_c":-2.0
},
"lower_bound":-1000.0,
"upper_bound":1000.0,
"gene_reaction_rule":"(PA2155) or (PA5394)",
"subsystem":"Glycerophospholipid metabolism",
"notes":{
"AUTHORS":[
""
],
"CONFIDENCE LEVEL":[
""
],
"EC NUMBER":[
"2.7.8.-"
],
"GENE ASSOCIATION":[
"(PA2155) or (PA5394)"
]
}
},
{
"id":"rPY00183",
"name":"Cardiolipin synthase (n-C18:0 18:1)",
"metabolites":{
"cPY00134_c":-2.0,
"cPY00141_c":1.0,
"cpd00100_c":1.0
},
"lower_bound":-1000.0,
"upper_bound":1000.0,
"gene_reaction_rule":"(PA2155) or (PA5394)",
"subsystem":"Glycerophospholipid metabolism",
"notes":{
"AUTHORS":[
""
],
"CONFIDENCE LEVEL":[
""
],
"EC NUMBER":[
"2.7.8.-"
],
"GENE ASSOCIATION":[
"(PA2155) or (PA5394)"
]
}
},
{
"id":"rxn08231",
"name":"Cardiolipin synthase (n-C18:0)",
"metabolites":{
"cpd00100_c":1.0,
"cpd15430_c":1.0,
"cpd15540_c":-2.0
},
"lower_bound":-1000.0,
"upper_bound":1000.0,
"gene_reaction_rule":"(PA2155) or (PA5394)",
"subsystem":"Glycerophospholipid metabolism",
"notes":{
"AUTHORS":[
""
],
"CONFIDENCE LEVEL":[
""
],
"EC NUMBER":[
"2.7.8.-"
],
"GENE ASSOCIATION":[
"(PA2155) or (PA5394)"
]
}
},
{
"id":"rxn08232",
"name":"Cardiolipin synthase (n-C18:1)",
"metabolites":{
"cpd00100_c":1.0,
"cpd15431_c":1.0,
"cpd15541_c":-2.0
},
"lower_bound":-1000.0,
"upper_bound":1000.0,
"gene_reaction_rule":"(PA2155) or (PA5394)",
"subsystem":"Glycerophospholipid metabolism",
"notes":{
"AUTHORS":[
""
],
"CONFIDENCE LEVEL":[
""
],
"EC NUMBER":[
"2.7.8.-"
],
"GENE ASSOCIATION":[
"(PA2155) or (PA5394)"
]
}
},
{
"id":"rxn00539",
"name":"ethanolamine ammonia-lyase",
"metabolites":{
"cpd00013_c":1.0,
"cpd00071_c":1.0,
"cpd00162_c":-1.0
},
"lower_bound":-1000.0,
"upper_bound":1000.0,
"gene_reaction_rule":"(PA4024 and PA4025)",
"subsystem":"Glycerophospholipid metabolism",
"notes":{
"AUTHORS":[
""
],
"CONFIDENCE LEVEL":[
""
],
"EC NUMBER":[
"4.3.1.7"
],
"GENE ASSOCIATION":[
"(PA4024 and PA4025)"
]
}
},
{
"id":"rxn01073",
"name":"Glycerophosphodiester phosphodiesterase (Glycerophosphoethanolamine)",
"metabolites":{
"cpd00001_c":-1.0,
"cpd00080_c":1.0,
"cpd00162_c":1.0,
"cpd00908_c":-1.0
},
"lower_bound":-1000.0,
"upper_bound":1000.0,
"gene_reaction_rule":"PA0347",
"subsystem":"Glycerophospholipid metabolism",
"notes":{
"AUTHORS":[
""
],
"CONFIDENCE LEVEL":[
""
],
"EC NUMBER":[
"3.1.4.2,3.1.4.46"
],
"GENE ASSOCIATION":[
"PA0347"
]
}
},
{
"id":"rxn00758",
"name":"Glycerophosphodiester phosphodiesterase (sn-Glycero-3-phosphocholine)",
"metabolites":{
"cpd00001_c":-1.0,
"cpd00080_c":1.0,
"cpd00098_c":1.0,
"cpd00507_c":-1.0
},
"lower_bound":-1000.0,
"upper_bound":1000.0,
"gene_reaction_rule":"PA0347",
"subsystem":"Glycerophospholipid metabolism",
"notes":{
"AUTHORS":[
""
],
"CONFIDENCE LEVEL":[
""
],
"EC NUMBER":[
"3.1.4.2,3.1.4.46"
],
"GENE ASSOCIATION":[
"PA0347"
]
}
},
{
"id":"rxn13817",
"name":"cardiolipin synthetase",
"metabolites":{
"cpd00046_c":1.0,
"cpd00067_c":1.0,
"cpd11427_c":-0.02,
"cpd11652_c":-0.02,
"cpd12801_c":0.02
},
"lower_bound":-1000.0,
"upper_bound":1000.0,
"gene_reaction_rule":"PA2155",
"subsystem":"Glycerophospholipid metabolism",
"notes":{
"AUTHORS":[
""
],
"CONFIDENCE LEVEL":[
""
],
"EC NUMBER":[
"2.7.8.-"
],
"GENE ASSOCIATION":[
"PA2155"
]
}
},
{
"id":"rxn13815",
"name":"CDPdiacylglycerol:sn-glycerol-3-phosphate 3-phosphatidyltransferase reversible",
"metabolites":{
"cpd00046_c":1.0,
"cpd00067_c":1.0,
"cpd00080_c":-1.0,
"cpd11427_c":-0.02,
"cpd11454_c":0.02
},
"lower_bound":-1000.0,
"upper_bound":1000.0,
"gene_reaction_rule":"PA2584",
"subsystem":"Glycerophospholipid metabolism",
"notes":{
"AUTHORS":[
""
],
"CONFIDENCE LEVEL":[
""
],
"EC NUMBER":[
"2.7.8.5"
],
"GENE ASSOCIATION":[
"PA2584"
]
}
},
{
"id":"rxn09108",
"name":"Phosphatidylglycerol synthase (n-C120)",
"metabolites":{
"cpd00046_c":1.0,
"cpd00080_c":-1.0,
"cpd15417_c":-1.0,
"cpd15542_c":1.0
},
"lower_bound":-1000.0,
"upper_bound":1000.0,
"gene_reaction_rule":"PA2584",
"subsystem":"Glycerophospholipid metabolism",
"notes":{
"AUTHORS":[
""
],
"CONFIDENCE LEVEL":[
""
],
"EC NUMBER":[
"2.7.8.5"
],
"GENE ASSOCIATION":[
"PA2584"
]
}
},
{
"id":"rxn09109",
"name":"Phosphatidylglycerol synthase (n-C140)",
"metabolites":{
"cpd00046_c":1.0,
"cpd00080_c":-1.0,
"cpd15423_c":-1.0,
"cpd15543_c":1.0
},
"lower_bound":-1000.0,
"upper_bound":1000.0,
"gene_reaction_rule":"PA2584",
"subsystem":"Glycerophospholipid metabolism",
"notes":{
"AUTHORS":[
""
],
"CONFIDENCE LEVEL":[
""
],
"EC NUMBER":[
"2.7.8.5"
],
"GENE ASSOCIATION":[
"PA2584"
]
}
},
{
"id":"rxn09110",
"name":"Phosphatidylglycerol synthase (n-C141)",
"metabolites":{
"cpd00046_c":1.0,
"cpd00080_c":-1.0,
"cpd15422_c":-1.0,
"cpd15544_c":1.0
},
"lower_bound":-1000.0,
"upper_bound":1000.0,
"gene_reaction_rule":"PA2584",
"subsystem":"Glycerophospholipid metabolism",
"notes":{
"AUTHORS":[
""
],
"CONFIDENCE LEVEL":[
""
],
"EC NUMBER":[
"2.7.8.5"
],
"GENE ASSOCIATION":[
"PA2584"
]
}
},
{
"id":"rxn09111",
"name":"Phosphatidylglycerol synthase (n-C160)",
"metabolites":{
"cpd00046_c":1.0,
"cpd00080_c":-1.0,
"cpd15419_c":-1.0,
"cpd15545_c":1.0
},
"lower_bound":-1000.0,
"upper_bound":1000.0,
"gene_reaction_rule":"PA2584",
"subsystem":"Glycerophospholipid metabolism",
"notes":{
"AUTHORS":[
""
],
"CONFIDENCE LEVEL":[
""
],
"EC NUMBER":[
"2.7.8.5"
],
"GENE ASSOCIATION":[
"PA2584"
]
}
},
{
"id":"rxn09112",
"name":"Phosphatidylglycerol synthase (n-C161)",
"metabolites":{
"cpd00046_c":1.0,
"cpd00080_c":-1.0,
"cpd15418_c":-1.0,
"cpd15546_c":1.0
},
"lower_bound":-1000.0,
"upper_bound":1000.0,
"gene_reaction_rule":"PA2584",
"subsystem":"Glycerophospholipid metabolism",
"notes":{
"AUTHORS":[
""
],
"CONFIDENCE LEVEL":[
""
],
"EC NUMBER":[
"2.7.8.5"
],
"GENE ASSOCIATION":[
"PA2584"
]
}
},
{
"id":"rxn09113",
"name":"Phosphatidylglycerol synthase (n-C180)",
"metabolites":{
"cpd00046_c":1.0,
"cpd00080_c":-1.0,
"cpd15421_c":-1.0,
"cpd15547_c":1.0
},
"lower_bound":-1000.0,
"upper_bound":1000.0,
"gene_reaction_rule":"PA2584",
"subsystem":"Glycerophospholipid metabolism",
"notes":{
"AUTHORS":[
""
],
"CONFIDENCE LEVEL":[
""
],
"EC NUMBER":[
"2.7.8.5"
],
"GENE ASSOCIATION":[
"PA2584"
]
}
},
{
"id":"rxn09114",
"name":"Phosphatidylglycerol synthase (n-C181)",
"metabolites":{
"cpd00046_c":1.0,
"cpd00080_c":-1.0,
"cpd15420_c":-1.0,
"cpd15548_c":1.0
},
"lower_bound":-1000.0,
"upper_bound":1000.0,
"gene_reaction_rule":"PA2584",
"subsystem":"Glycerophospholipid metabolism",
"notes":{
"AUTHORS":[
""
],
"CONFIDENCE LEVEL":[
""
],
"EC NUMBER":[
"2.7.8.5"
],
"GENE ASSOCIATION":[
"PA2584"
]
}
},
{
"id":"rPY00215",
"name":"phospholipase D",
"metabolites":{
"cpd00001_c":-1.0,
"cpd00098_c":1.0,
"cpd11422_c":1.0,
"cpd11624_c":-1.0
},
"lower_bound":-1000.0,
"upper_bound":1000.0,
"gene_reaction_rule":"PA3487",
"subsystem":"Glycerophospholipid metabolism",
"notes":{
"AUTHORS":[
""
],
"CONFIDENCE LEVEL":[
""
],
"EC NUMBER":[
"3.1.4.4"
],
"GENE ASSOCIATION":[
"PA3487"
]
}
},
{
"id":"rxn13889",
"name":"phosphatidate cytidylyltransferase reversible",
"metabolites":{
"cpd00012_c":1.0,
"cpd00052_c":-1.0,
"cpd00067_c":-1.0,
"cpd11422_c":-0.02,
"cpd11427_c":0.02
},
"lower_bound":-1000.0,
"upper_bound":1000.0,
"gene_reaction_rule":"PA3651",
"subsystem":"Glycerophospholipid metabolism",
"notes":{
"AUTHORS":[
""
],
"CONFIDENCE LEVEL":[
""
],
"EC NUMBER":[
"2.7.7.41"
],
"GENE ASSOCIATION":[
"PA3651"
]
}
},
{
"id":"rPY00214",
"name":"phosphatidylcholine synthase",
"metabolites":{
"cpd00046_c":1.0,
"cpd00098_c":-1.0,
"cpd11427_c":-1.0,
"cpd11624_c":1.0
},
"lower_bound":-1000.0,
"upper_bound":1000.0,
"gene_reaction_rule":"PA3857",
"subsystem":"Glycerophospholipid metabolism",
"notes":{
"AUTHORS":[
""
],
"CONFIDENCE LEVEL":[
""
],
"EC NUMBER":[
"2.7.8.24"
],
"GENE ASSOCIATION":[
"PA3857"
]
}
},
{
"id":"rxn09101",
"name":"phosphatidylglycerol phosphate phosphatase (n-C140)",
"metabolites":{
"cpd00001_c":-1.0,
"cpd00009_c":1.0,
"cpd00067_c":1.0,
"cpd15535_c":1.0,
"cpd15542_c":-1.0
},
"lower_bound":-1000.0,
"upper_bound":1000.0,
"gene_reaction_rule":"PA4050",
"subsystem":"Glycerophospholipid metabolism",
"notes":{
"AUTHORS":[
""
],
"CONFIDENCE LEVEL":[
""
],
"EC NUMBER":[
"3.1.3.27"
],
"GENE ASSOCIATION":[
"PA4050"
]
}
},
{
"id":"rxn09102",
"name":"phosphatidylglycerol phosphate phosphatase (n-C140)",
"metabolites":{
"cpd00001_c":-1.0,
"cpd00009_c":1.0,
"cpd00067_c":1.0,
"cpd15536_c":1.0,
"cpd15543_c":-1.0
},
"lower_bound":-1000.0,
"upper_bound":1000.0,
"gene_reaction_rule":"PA4050",
"subsystem":"Glycerophospholipid metabolism",
"notes":{
"AUTHORS":[
""
],
"CONFIDENCE LEVEL":[
""
],
"EC NUMBER":[
"3.1.3.27"
],
"GENE ASSOCIATION":[
"PA4050"
]
}
},
{
"id":"rxn09103",
"name":"phosphatidylglycerol phosphate phosphatase (n-C141)",
"metabolites":{
"cpd00001_c":-1.0,
"cpd00009_c":1.0,
"cpd00067_c":1.0,
"cpd15537_c":1.0,
"cpd15544_c":-1.0
},
"lower_bound":-1000.0,
"upper_bound":1000.0,
"gene_reaction_rule":"PA4050",
"subsystem":"Glycerophospholipid metabolism",
"notes":{
"AUTHORS":[
""
],
"CONFIDENCE LEVEL":[
""
],
"EC NUMBER":[
"3.1.3.27"
],
"GENE ASSOCIATION":[
"PA4050"
]
}
},
{
"id":"rxn09104",
"name":"phosphatidylglycerol phosphate phosphatase (n-C160)",
"metabolites":{
"cpd00001_c":-1.0,
"cpd00009_c":1.0,
"cpd00067_c":1.0,
"cpd15538_c":1.0,
"cpd15545_c":-1.0
},
"lower_bound":-1000.0,
"upper_bound":1000.0,
"gene_reaction_rule":"PA4050",
"subsystem":"Glycerophospholipid metabolism",
"notes":{
"AUTHORS":[
""
],
"CONFIDENCE LEVEL":[
""
],
"EC NUMBER":[
"3.1.3.27"
],
"GENE ASSOCIATION":[
"PA4050"
]
}
},
{
"id":"rxn09105",
"name":"phosphatidylglycerol phosphate phosphatase (n-C161)",
"metabolites":{
"cpd00001_c":-1.0,
"cpd00009_c":1.0,
"cpd00067_c":1.0,
"cpd15539_c":1.0,
"cpd15546_c":-1.0
},
"lower_bound":-1000.0,
"upper_bound":1000.0,
"gene_reaction_rule":"PA4050",
"subsystem":"Glycerophospholipid metabolism",
"notes":{
"AUTHORS":[
""
],
"CONFIDENCE LEVEL":[
""
],
"EC NUMBER":[
"3.1.3.27"
],
"GENE ASSOCIATION":[
"PA4050"
]
}
},
{
"id":"rxn09106",
"name":"phosphatidylglycerol phosphate phosphatase (n-C180)",
"metabolites":{
"cpd00001_c":-1.0,
"cpd00009_c":1.0,
"cpd00067_c":1.0,
"cpd15540_c":1.0,
"cpd15547_c":-1.0
},
"lower_bound":-1000.0,
"upper_bound":1000.0,
"gene_reaction_rule":"PA4050",
"subsystem":"Glycerophospholipid metabolism",
"notes":{
"AUTHORS":[
""
],
"CONFIDENCE LEVEL":[
""
],
"EC NUMBER":[
"3.1.3.27"
],
"GENE ASSOCIATION":[
"PA4050"
]
}
},
{
"id":"rxn09107",
"name":"phosphatidylglycerol phosphate phosphatase (n-C181)",
"metabolites":{
"cpd00001_c":-1.0,
"cpd00009_c":1.0,
"cpd00067_c":1.0,
"cpd15541_c":1.0,
"cpd15548_c":-1.0
},
"lower_bound":-1000.0,
"upper_bound":1000.0,
"gene_reaction_rule":"PA4050",
"subsystem":"Glycerophospholipid metabolism",
"notes":{
"AUTHORS":[
""
],
"CONFIDENCE LEVEL":[
""
],
"EC NUMBER":[
"3.1.3.27"
],
"GENE ASSOCIATION":[
"PA4050"
]
}
},
{
"id":"rxn13887",
"name":"Phosphatidylglycerophosphate phosphohydrolase",
"metabolites":{
"cpd00001_c":-1.0,
"cpd00009_c":1.0,
"cpd11454_c":-0.02,
"cpd11652_c":0.02
},
"lower_bound":-1000.0,
"upper_bound":1000.0,
"gene_reaction_rule":"PA4050",
"subsystem":"Glycerophospholipid metabolism",
"notes":{
"AUTHORS":[
""
],
"CONFIDENCE LEVEL":[
""
],
"EC NUMBER":[
"3.1.3.27"
],
"GENE ASSOCIATION":[
"PA4050"
]
}
},
{
"id":"rxn09205",
"name":"Phosphatidylserine syntase (n-C120)",
"metabolites":{
"cpd00046_c":1.0,
"cpd00054_c":-1.0,
"cpd00067_c":1.0,
"cpd15417_c":-1.0,
"cpd15552_c":1.0
},
"lower_bound":-1000.0,
"upper_bound":1000.0,
"gene_reaction_rule":"PA4693",
"subsystem":"Glycerophospholipid metabolism",
"notes":{
"AUTHORS":[
""
],
"CONFIDENCE LEVEL":[
""
],
"EC NUMBER":[
"2.7.8.8"
],
"GENE ASSOCIATION":[
"PA4693"
]
}
},
{
"id":"rxn09206",
"name":"Phosphatidylserine syntase (n-C140)",
"metabolites":{
"cpd00046_c":1.0,
"cpd00054_c":-1.0,
"cpd00067_c":1.0,
"cpd15423_c":-1.0,
"cpd15553_c":1.0
},
"lower_bound":-1000.0,
"upper_bound":1000.0,
"gene_reaction_rule":"PA4693",
"subsystem":"Glycerophospholipid metabolism",
"notes":{
"AUTHORS":[
""
],
"CONFIDENCE LEVEL":[
""
],
"EC NUMBER":[
"2.7.8.8"
],
"GENE ASSOCIATION":[
"PA4693"
]
}
},
{
"id":"rxn09207",
"name":"Phosphatidylserine syntase (n-C141)",
"metabolites":{
"cpd00046_c":1.0,
"cpd00054_c":-1.0,
"cpd00067_c":1.0,
"cpd15422_c":-1.0,
"cpd15554_c":1.0
},
"lower_bound":-1000.0,
"upper_bound":1000.0,
"gene_reaction_rule":"PA4693",
"subsystem":"Glycerophospholipid metabolism",
"notes":{
"AUTHORS":[
""
],
"CONFIDENCE LEVEL":[
""
],
"EC NUMBER":[
"2.7.8.8"
],
"GENE ASSOCIATION":[
"PA4693"
]
}
},
{
"id":"rxn09208",
"name":"Phosphatidylserine syntase (n-C160)",
"metabolites":{
"cpd00046_c":1.0,
"cpd00054_c":-1.0,
"cpd00067_c":1.0,
"cpd15419_c":-1.0,
"cpd15555_c":1.0
},
"lower_bound":-1000.0,
"upper_bound":1000.0,
"gene_reaction_rule":"PA4693",
"subsystem":"Glycerophospholipid metabolism",
"notes":{
"AUTHORS":[
""
],
"CONFIDENCE LEVEL":[
""
],
"EC NUMBER":[
"2.7.8.8"
],
"GENE ASSOCIATION":[
"PA4693"
]
}
},
{
"id":"rxn09209",
"name":"Phosphatidylserine syntase (n-C161)",
"metabolites":{
"cpd00046_c":1.0,
"cpd00054_c":-1.0,
"cpd00067_c":1.0,
"cpd15418_c":-1.0,
"cpd15556_c":1.0
},
"lower_bound":-1000.0,
"upper_bound":1000.0,
"gene_reaction_rule":"PA4693",
"subsystem":"Glycerophospholipid metabolism",
"notes":{
"AUTHORS":[
""
],
"CONFIDENCE LEVEL":[
""
],
"EC NUMBER":[
"2.7.8.8"
],
"GENE ASSOCIATION":[
"PA4693"
]
}
},
{
"id":"rxn09210",
"name":"Phosphatidylserine syntase (n-C180)",
"metabolites":{
"cpd00046_c":1.0,
"cpd00054_c":-1.0,
"cpd00067_c":1.0,
"cpd15421_c":-1.0,
"cpd15557_c":1.0
},
"lower_bound":-1000.0,
"upper_bound":1000.0,
"gene_reaction_rule":"PA4693",
"subsystem":"Glycerophospholipid metabolism",
"notes":{
"AUTHORS":[
""
],
"CONFIDENCE LEVEL":[
""
],
"EC NUMBER":[
"2.7.8.8"
],
"GENE ASSOCIATION":[
"PA4693"
]
}
},
{
"id":"rxn09211",
"name":"Phosphatidylserine syntase (n-C181)",
"metabolites":{
"cpd00046_c":1.0,
"cpd00054_c":-1.0,
"cpd00067_c":1.0,
"cpd15420_c":-1.0,
"cpd15558_c":1.0
},
"lower_bound":-1000.0,
"upper_bound":1000.0,
"gene_reaction_rule":"PA4693",
"subsystem":"Glycerophospholipid metabolism",
"notes":{
"AUTHORS":[
""
],
"CONFIDENCE LEVEL":[
""
],
"EC NUMBER":[
"2.7.8.8"
],
"GENE ASSOCIATION":[
"PA4693"
]
}
},
{
"id":"rxn10233",
"name":"anteisoheptadecanoyl-phosphatidylserine decarboxylase",
"metabolites":{
"cpd00011_c":1.0,
"cpd00067_c":-2.0,
"cpd15690_c":-1.0,
"cpd15696_c":1.0
},
"lower_bound":-1000.0,
"upper_bound":1000.0,
"gene_reaction_rule":"PA4957",
"subsystem":"Glycerophospholipid metabolism",
"notes":{
"AUTHORS":[
""
],
"CONFIDENCE LEVEL":[
""
],
"EC NUMBER":[
""
],
"GENE ASSOCIATION":[
"PA4957"
]
}
},
{
"id":"rxn10236",
"name":"anteisopentadecanoyl-phosphatidylserine decarboxylase",
"metabolites":{
"cpd00011_c":1.0,
"cpd00067_c":-2.0,
"cpd15693_c":-1.0,
"cpd15699_c":1.0
},
"lower_bound":-1000.0,
"upper_bound":1000.0,
"gene_reaction_rule":"PA4957",
"subsystem":"Glycerophospholipid metabolism",
"notes":{
"AUTHORS":[
""
],
"CONFIDENCE LEVEL":[
""
],
"EC NUMBER":[
""
],
"GENE ASSOCIATION":[
"PA4957"
]
}
},
{
"id":"rxn10232",
"name":"isoheptadecanoyl-phosphatidylserine decarboxylase",
"metabolites":{
"cpd00011_c":1.0,
"cpd00067_c":-2.0,
"cpd15689_c":-1.0,
"cpd15695_c":1.0
},
"lower_bound":-1000.0,
"upper_bound":1000.0,
"gene_reaction_rule":"PA4957",
"subsystem":"Glycerophospholipid metabolism",
"notes":{
"AUTHORS":[
""
],
"CONFIDENCE LEVEL":[
""
],
"EC NUMBER":[
""
],
"GENE ASSOCIATION":[
"PA4957"
]
}
},
{
"id":"rxn10237",
"name":"isohexadecanoyl-phosphatidylserine decarboxylase",
"metabolites":{
"cpd00011_c":1.0,
"cpd00067_c":-2.0,
"cpd15694_c":-1.0,
"cpd15700_c":1.0
},
"lower_bound":-1000.0,
"upper_bound":1000.0,
"gene_reaction_rule":"PA4957",
"subsystem":"Glycerophospholipid metabolism",
"notes":{
"AUTHORS":[
""
],
"CONFIDENCE LEVEL":[
""
],
"EC NUMBER":[
""
],
"GENE ASSOCIATION":[
"PA4957"
]
}
},
{
"id":"rxn10235",
"name":"isopentadecanoyl-phosphatidylserine decarboxylase",
"metabolites":{
"cpd00011_c":1.0,
"cpd00067_c":-2.0,
"cpd15692_c":-1.0,
"cpd15698_c":1.0
},
"lower_bound":-1000.0,
"upper_bound":1000.0,
"gene_reaction_rule":"PA4957",
"subsystem":"Glycerophospholipid metabolism",
"notes":{
"AUTHORS":[
""
],
"CONFIDENCE LEVEL":[
""
],
"EC NUMBER":[
""
],
"GENE ASSOCIATION":[
"PA4957"
]
}
},
{
"id":"rxn10234",
"name":"isotetradecanoyl-phosphatidylserine decarboxylase",
"metabolites":{
"cpd00011_c":1.0,
"cpd00067_c":-2.0,
"cpd15691_c":-1.0,
"cpd15697_c":1.0
},
"lower_bound":-1000.0,
"upper_bound":1000.0,
"gene_reaction_rule":"PA4957",
"subsystem":"Glycerophospholipid metabolism",
"notes":{
"AUTHORS":[
""
],
"CONFIDENCE LEVEL":[
""
],
"EC NUMBER":[
""
],
"GENE ASSOCIATION":[
"PA4957"
]
}
},
{
"id":"rxn13894",
"name":"phosphatidylserine decarboxylase",
"metabolites":{
"cpd00011_c":1.0,
"cpd11455_c":-0.02,
"cpd11456_c":0.02
},
"lower_bound":-1000.0,
"upper_bound":1000.0,
"gene_reaction_rule":"PA4957",
"subsystem":"Glycerophospholipid metabolism",
"notes":{
"AUTHORS":[
""
],
"CONFIDENCE LEVEL":[
""
],
"EC NUMBER":[
"4.1.1.65"
],
"GENE ASSOCIATION":[
"PA4957"
]
}
},
{
"id":"rxn09197",
"name":"Phosphatidylserine decarboxylase (n-C120)",
"metabolites":{
"cpd00011_c":1.0,
"cpd00067_c":-2.0,
"cpd15528_c":1.0,
"cpd15552_c":-1.0
},
"lower_bound":-1000.0,
"upper_bound":1000.0,
"gene_reaction_rule":"PA4957",
"subsystem":"Glycerophospholipid metabolism",
"notes":{
"AUTHORS":[
""
],
"CONFIDENCE LEVEL":[
""
],
"EC NUMBER":[
"4.1.1.65"
],
"GENE ASSOCIATION":[
"PA4957"
]
}
},
{
"id":"rxn09198",
"name":"Phosphatidylserine decarboxylase (n-C140)",
"metabolites":{
"cpd00011_c":1.0,
"cpd00067_c":-2.0,
"cpd15529_c":1.0,
"cpd15553_c":-1.0
},
"lower_bound":-1000.0,
"upper_bound":1000.0,
"gene_reaction_rule":"PA4957",
"subsystem":"Glycerophospholipid metabolism",
"notes":{
"AUTHORS":[
""
],
"CONFIDENCE LEVEL":[
""
],
"EC NUMBER":[
"4.1.1.65"
],
"GENE ASSOCIATION":[
"PA4957"
]
}
},
{
"id":"rxn09199",
"name":"Phosphatidylserine decarboxylase (n-C141)",
"metabolites":{
"cpd00011_c":1.0,
"cpd00067_c":-2.0,
"cpd15530_c":1.0,
"cpd15554_c":-1.0
},
"lower_bound":-1000.0,
"upper_bound":1000.0,
"gene_reaction_rule":"PA4957",
"subsystem":"Glycerophospholipid metabolism",
"notes":{
"AUTHORS":[
""
],
"CONFIDENCE LEVEL":[
""
],
"EC NUMBER":[
"4.1.1.65"
],
"GENE ASSOCIATION":[
"PA4957"
]
}
},
{
"id":"rPY00165",
"name":"Phosphatidylserine decarboxylase (n-C16:0 16:1)",
"metabolites":{
"cPY00122_c":-1.0,
"cPY00123_c":1.0,
"cpd00011_c":1.0,
"cpd00067_c":-1.0
},
"lower_bound":-1000.0,
"upper_bound":1000.0,
"gene_reaction_rule":"PA4957",
"subsystem":"Glycerophospholipid metabolism",
"notes":{
"AUTHORS":[
""
],
"CONFIDENCE LEVEL":[
""
],
"EC NUMBER":[
"4.1.1.65"
],
"GENE ASSOCIATION":[
"PA4957"
]
}
},
{
"id":"rxn09200",
"name":"Phosphatidylserine decarboxylase (n-C160)",
"metabolites":{
"cpd00011_c":1.0,
"cpd00067_c":-2.0,
"cpd15531_c":1.0,
"cpd15555_c":-1.0
},
"lower_bound":-1000.0,
"upper_bound":1000.0,
"gene_reaction_rule":"PA4957",
"subsystem":"Glycerophospholipid metabolism",
"notes":{
"AUTHORS":[
""
],
"CONFIDENCE LEVEL":[
""
],
"EC NUMBER":[
"4.1.1.65"
],
"GENE ASSOCIATION":[
"PA4957"
]
}
},
{
"id":"rxn09201",
"name":"Phosphatidylserine decarboxylase (n-C161)",
"metabolites":{
"cpd00011_c":1.0,
"cpd00067_c":-2.0,
"cpd15532_c":1.0,
"cpd15556_c":-1.0
},
"lower_bound":-1000.0,
"upper_bound":1000.0,
"gene_reaction_rule":"PA4957",
"subsystem":"Glycerophospholipid metabolism",
"notes":{
"AUTHORS":[
""
],
"CONFIDENCE LEVEL":[
""
],
"EC NUMBER":[
"4.1.1.65"
],
"GENE ASSOCIATION":[
"PA4957"
]
}
},
{
"id":"rPY00170",
"name":"Phosphatidylserine decarboxylase (n-C18:0 18:1)",
"metabolites":{
"cPY00127_c":-1.0,
"cPY00128_c":1.0,
"cpd00011_c":1.0,
"cpd00067_c":-1.0
},
"lower_bound":-1000.0,
"upper_bound":1000.0,
"gene_reaction_rule":"PA4957",
"subsystem":"Glycerophospholipid metabolism",
"notes":{
"AUTHORS":[
""
],
"CONFIDENCE LEVEL":[
""
],
"EC NUMBER":[
"4.1.1.65"
],
"GENE ASSOCIATION":[
"PA4957"
]
}
},
{
"id":"rxn09202",
"name":"Phosphatidylserine decarboxylase (n-C180)",
"metabolites":{
"cpd00011_c":1.0,
"cpd00067_c":-2.0,
"cpd15533_c":1.0,
"cpd15557_c":-1.0
},
"lower_bound":-1000.0,
"upper_bound":1000.0,
"gene_reaction_rule":"PA4957",
"subsystem":"Glycerophospholipid metabolism",
"notes":{
"AUTHORS":[
""
],
"CONFIDENCE LEVEL":[
""
],
"EC NUMBER":[
"4.1.1.65"
],
"GENE ASSOCIATION":[
"PA4957"
]
}
},
{
"id":"rxn09203",
"name":"Phosphatidylserine decarboxylase (n-C181)",
"metabolites":{
"cpd00011_c":1.0,
"cpd00067_c":-2.0,
"cpd15534_c":1.0,
"cpd15558_c":-1.0
},
"lower_bound":-1000.0,
"upper_bound":1000.0,
"gene_reaction_rule":"PA4957",
"subsystem":"Glycerophospholipid metabolism",
"notes":{
"AUTHORS":[
""
],
"CONFIDENCE LEVEL":[
""
],
"EC NUMBER":[
"4.1.1.65"
],
"GENE ASSOCIATION":[
"PA4957"
]
}
},
{
"id":"rxn13818",
"name":"cardiolipin synthase reversible",
"metabolites":{
"cpd00100_c":1.0,
"cpd11652_c":-0.04,
"cpd12801_c":0.02
},
"lower_bound":-1000.0,
"upper_bound":1000.0,
"gene_reaction_rule":"PA5394",
"subsystem":"Glycerophospholipid metabolism",
"notes":{
"AUTHORS":[
""
],
"CONFIDENCE LEVEL":[
""
],
"EC NUMBER":[
"2.7.8.-"
],
"GENE ASSOCIATION":[
"PA5394"
]
}
}
],
"genes":[
{
"id":"PA3025",
"name":""
},
{
"id":"PA3584",
"name":""
},
{
"id":"PA1614",
"name":""
},
{
"id":"PA2352",
"name":""
},
{
"id":"PA0347",
"name":""
},
{
"id":"PA5394",
"name":""
},
{
"id":"PA2155",
"name":""
},
{
"id":"PA4025",
"name":""
},
{
"id":"PA4024",
"name":""
},
{
"id":"PA2584",
"name":""
},
{
"id":"PA3487",
"name":""
},
{
"id":"PA3651",
"name":""
},
{
"id":"PA3857",
"name":""
},
{
"id":"PA4050",
"name":""
},
{
"id":"PA4693",
"name":""
},
{
"id":"PA4957",
"name":""
}
],
"id":"",
"compartments":{
"c":"Cytoplasm"
},
"version":"1"
}