{
"metabolites":[
{
"id":"cpd00003_c",
"name":"NAD",
"compartment":"c",
"charge":-1,
"formula":"C21H26N7O14P2"
},
{
"id":"cpd00004_c",
"name":"NADH",
"compartment":"c",
"charge":-2,
"formula":"C21H27N7O14P2"
},
{
"id":"cpd00067_c",
"name":"H+",
"compartment":"c",
"charge":1,
"formula":"H"
},
{
"id":"cpd00001_c",
"name":"H2O",
"compartment":"c",
"charge":0,
"formula":"H2O"
},
{
"id":"cpd00006_c",
"name":"NADP",
"compartment":"c",
"charge":-2,
"formula":"C21H26N7O17P3"
},
{
"id":"cpd00005_c",
"name":"NADPH",
"compartment":"c",
"charge":-3,
"formula":"C21H27N7O17P3"
},
{
"id":"cpd00345_c",
"name":"5-Methyltetrahydrofolate",
"compartment":"c",
"charge":-2,
"formula":"C20H23N7O6"
},
{
"id":"cpd00125_c",
"name":"5-10-Methylenetetrahydrofolate",
"compartment":"c",
"charge":-2,
"formula":"C20H21N7O6"
},
{
"id":"cpd00347_c",
"name":"5-10-Methenyltetrahydrofolate",
"compartment":"c",
"charge":-1,
"formula":"C20H20N7O6"
},
{
"id":"cpd00201_c",
"name":"10-Formyltetrahydrofolate",
"compartment":"c",
"charge":-2,
"formula":"C20H21N7O7"
}
],
"reactions":[
{
"id":"rxn04954",
"name":"5,10-methylenetetrahydrofolate reductase (NADH)",
"metabolites":{
"cpd00003_c":-1.0,
"cpd00004_c":1.0,
"cpd00067_c":1.0,
"cpd00125_c":1.0,
"cpd00345_c":-1.0
},
"lower_bound":-1000.0,
"upper_bound":1000.0,
"gene_reaction_rule":"PA0430",
"subsystem":"One carbon pool by folate",
"notes":{
"AUTHORS":[
""
],
"CONFIDENCE LEVEL":[
""
],
"EC NUMBER":[
"1.5.1.20"
],
"GENE ASSOCIATION":[
"PA0430"
]
}
},
{
"id":"rxn00907",
"name":"methylenetetrahydrofolate dehydrogenase (NADP)",
"metabolites":{
"cpd00005_c":1.0,
"cpd00006_c":-1.0,
"cpd00125_c":-1.0,
"cpd00347_c":1.0
},
"lower_bound":-1000.0,
"upper_bound":1000.0,
"gene_reaction_rule":"PA1796",
"subsystem":"One carbon pool by folate",
"notes":{
"AUTHORS":[
""
],
"CONFIDENCE LEVEL":[
""
],
"EC NUMBER":[
"1.5.1.5"
],
"GENE ASSOCIATION":[
"PA1796"
]
}
},
{
"id":"rxn01211",
"name":"methenyltetrahydrofolate cyclohydrolase",
"metabolites":{
"cpd00001_c":-1.0,
"cpd00067_c":1.0,
"cpd00201_c":1.0,
"cpd00347_c":-1.0
},
"lower_bound":-1000.0,
"upper_bound":1000.0,
"gene_reaction_rule":"PA1796",
"subsystem":"One carbon pool by folate",
"notes":{
"AUTHORS":[
""
],
"CONFIDENCE LEVEL":[
""
],
"EC NUMBER":[
"3.5.4.9,6.3.4.3"
],
"GENE ASSOCIATION":[
"PA1796"
]
}
}
],
"genes":[
{
"id":"PA0430",
"name":""
},
{
"id":"PA1796",
"name":""
}
],
"id":"",
"compartments":{
"c":"Cytoplasm"
},
"version":"1"
}